apppy/env/__init__.py
apppy/env/app_names_unit_test.py
apppy/env/fixtures.py
apppy/env/.secrets/dummy/APP_TEST_SECRET
apppy_env-0.23.2.dist-info/METADATA
apppy_env-0.23.2.dist-info/WHEEL
apppy_env-0.23.2.dist-info/RECORD
