Metadata-Version: 2.4
Name: apppy-env
Version: 0.23.2
Summary: Python environment configuration helpers for server development
Project-URL: Homepage, https://github.com/spals/apppy
Author: Tim Kral
License: MIT
Classifier: License :: OSI Approved :: MIT License
Classifier: Programming Language :: Python :: 3
Requires-Python: >=3.11
Requires-Dist: pydantic-settings==2.10.1
Requires-Dist: pydantic==2.11.7
